{"has_wiki": false, "topics": ["datetime", "python", "python-library"], "forks_count": 2, "updated_at": "2016-12-31T16:01:59", "owner_html_url": "https://github.com/thombashi", "result": "success", "branches_count": 1, "id": "thombashi/DateTimeRange", "license": {"spdx_id": "MIT", "url": "https://api.github.com/licenses/mit", "featured": true, "name": "MIT License", "key": "mit"}, "tags_count": 14, "languages": {"labels": ["Python", "Jupyter Notebook"], "data": [61376, 17885]}, "data_version": 2, "pulls_count": 0, "stargazers_count": 16, "emojis": {}, "participation": [0, 0, 0, 0, 0, 0, 0, 0, 0, 11, 0, 12, 0, 0, 4, 0, 7, 0, 0, 0, 0, 0, 0, 0, 0, 0, 0, 0, 0, 0, 6, 7, 0, 0, 0, 0, 7, 0, 0, 0, 0, 0, 0, 0, 12, 1, 0, 0, 0, 0, 0, 0], "owner_name": "Tsuyoshi Hombashi", "description": "A python library to handle routine work associated with a time range, such as test whether a time is within the time range, get time range intersection, truncating time range, etc.", "repo_homepage": "http://datetimerange.rtfd.io/", "subscribers_count": 2, "html_url": "https://github.com/thombashi/DateTimeRange", "languages_count": 2, "latest_tag": "v0.3.1", "commits_last_year": 67, "contributors_count": 2, "fetched_at": "2017-04-16T10:42:19", "has_issues": true, "open_issues_count": 0, "name": "DateTimeRange", "language": "Python", "created_at": "2016-02-19T05:15:09", "card_type": "Repository", "avatar_url": "https://avatars3.githubusercontent.com/u/15517661?v=3", "open_issues": {"labels": [], "data": []}, "organization": {}}
