{
    "id": "thombashi/SimpleSQLite",
    "fetched_at": "2019-05-12T16:25:49",
    "data_version": 2,
    "result": "success",
    "avatar_url": "https://avatars0.githubusercontent.com/u/15517661?v=4",
    "card_type": "Repository",
    "created_at": "2016-02-21T14:01:23",
    "description": "SimpleSQLite is a Python library to simplify SQLite database operations: table creation, data insertion and get data as other data formats. Simple ORM functionality for SQLite.",
    "emojis": {},
    "html_url": "https://github.com/thombashi/SimpleSQLite",
    "name": "SimpleSQLite",
    "updated_at": "2019-05-11T12:20:38",
    "forks_count": 9,
    "has_issues": true,
    "has_wiki": false,
    "language": "Python",
    "languages": {
        "labels": [
            "Python",
            "HTML",
            "Makefile",
            "Shell"
        ],
        "data": [
            192294,
            71819,
            1413,
            320
        ]
    },
    "languages_count": 4,
    "owner_name": "Tsuyoshi Hombashi",
    "owner_html_url": "https://github.com/thombashi",
    "open_issues_count": 0,
    "organization": {},
    "repo_homepage": "https://simplesqlite.rtfd.io/",
    "stargazers_count": 74,
    "topics": [
        "database",
        "database-library",
        "orm",
        "pandas-dataframe",
        "python-library",
        "sqlite"
    ],
    "participation": [
        0,
        14,
        18,
        5,
        19,
        18,
        16,
        11,
        21,
        22,
        6,
        7,
        21,
        0,
        6,
        0,
        15,
        0,
        13,
        0,
        0,
        5,
        0,
        0,
        2,
        0,
        0,
        0,
        10,
        0,
        0,
        0,
        8,
        7,
        15,
        28,
        36,
        9,
        9,
        4,
        29,
        0,
        7,
        5,
        22,
        0,
        0,
        6,
        4,
        0,
        12,
        12
    ],
    "commits_last_year": 442,
    "latest_tag": "v0.45.2",
    "branches_count": 1,
    "pulls_count": 0,
    "subscribers_count": 1,
    "license": {
        "key": "mit",
        "name": "MIT License",
        "spdx_id": "MIT",
        "url": "https://api.github.com/licenses/mit",
        "node_id": "MDc6TGljZW5zZTEz"
    },
    "contributors_count": 1,
    "tags_count": 103,
    "open_issues": {
        "labels": [],
        "data": []
    }
}
