{"has_wiki": false, "forks_count": 0, "updated_at": "2017-01-21T06:47:15", "owner_html_url": "https://github.com/thombashi", "id": "thombashi/allpairspy", "license": null, "tags_count": 1, "languages": {"labels": ["Python"], "data": [20279]}, "data_version": 1, "pulls_count": 0, "latest_tag": "v0.2.1", "stargazers_count": 0, "emojis": {}, "participation": [0, 0, 0, 0, 0, 0, 0, 0, 0, 0, 0, 0, 0, 0, 0, 0, 0, 0, 0, 0, 0, 0, 0, 0, 0, 0, 0, 0, 0, 0, 0, 0, 0, 0, 0, 0, 0, 0, 0, 0, 0, 0, 0, 19, 0, 0, 0, 0, 0, 0, 0, 0], "owner_name": "Tsuyoshi Hombashi", "repo_homepage": null, "subscribers_count": 1, "html_url": "https://github.com/thombashi/allpairspy", "languages_count": 1, "language": "Python", "commits_last_year": 19, "contributors_count": 1, "fetched_at": "2017-03-20T21:07:33", "has_issues": true, "repo_description": "A python library for test combinations generator. The generator allows one to create a set of tests using \"pairwise combinations\" method, reducing a number of combinations of variables into a lesser set that covers most situations.", "open_issues_count": 0, "name": "allpairspy", "branches_count": 1, "created_at": "2017-01-20T23:35:40", "card_type": "repository", "avatar_url": "https://avatars3.githubusercontent.com/u/15517661?v=3", "open_issues": {"labels": [], "data": []}, "organization": {}}
