{
    "has_wiki": false, 
    "forks_count": 0, 
    "updated_at": "2016-11-12T14:22:31", 
    "owner_html_url": "https://github.com/thombashi", 
    "id": "thombashi/subprocrunner", 
    "license": {
        "spdx_id": "MIT", 
        "url": "https://api.github.com/licenses/mit", 
        "featured": true, 
        "name": "MIT License", 
        "key": "mit"
    }, 
    "tags_count": 13, 
    "languages": {
        "Python": 15274
    }, 
    "version": "0.0.1", 
    "latest_tag": "v0.4.11", 
    "stargazers_count": 0, 
    "participation": [
        0, 
        0, 
        0, 
        0, 
        0, 
        0, 
        0, 
        0, 
        0, 
        0, 
        0, 
        0, 
        0, 
        0, 
        0, 
        0, 
        0, 
        0, 
        0, 
        0, 
        0, 
        12, 
        10, 
        5, 
        0, 
        0, 
        0, 
        0, 
        2, 
        0, 
        0, 
        0, 
        0, 
        0, 
        1, 
        0, 
        0, 
        0, 
        0, 
        0, 
        0, 
        0, 
        0, 
        14, 
        6, 
        0, 
        0, 
        1, 
        2, 
        6, 
        0, 
        0
    ], 
    "owner_name": "Tsuyoshi Hombashi", 
    "repo_homepage": "https://pypi.python.org/pypi/subprocrunner", 
    "subscribers_count": 1, 
    "html_url": "https://github.com/thombashi/subprocrunner", 
    "language": "Python", 
    "contributors_count": 1, 
    "fetched_at": "2017-03-14T00:38:30", 
    "has_issues": true, 
    "repo_description": "A python library of subprocess module wrapper.", 
    "open_issues_count": 0, 
    "name": "subprocrunner", 
    "branches_count": 1, 
    "pulls_count": 0, 
    "created_at": "2016-08-12T06:19:20", 
    "card_type": "repository", 
    "avatar_url": "https://avatars3.githubusercontent.com/u/15517661?v=3", 
    "open_issues": {}, 
    "organization": {}
}
