{"id": "thombashi/pytablereader", "fetched_at": "2018-04-08T22:46:40", "data_version": 2, "result": "success", "avatar_url": "https://avatars0.githubusercontent.com/u/15517661?v=4", "card_type": "Repository", "created_at": "2016-10-23T15:45:24", "description": "A Python library to load structured table data from files/strings/URL with various data format: CSV/Excel/Google-Sheets/HTML/JSON/LTSV/Markdown/SQLite/TSV.", "emojis": {}, "html_url": "https://github.com/thombashi/pytablereader", "name": "pytablereader", "updated_at": "2018-04-08T13:17:41", "forks_count": 2, "has_issues": true, "has_wiki": false, "language": "Python", "languages": {"labels": ["Python", "HTML"], "data": [242158, 71819]}, "languages_count": 2, "owner_name": "Tsuyoshi Hombashi", "owner_html_url": "https://github.com/thombashi", "open_issues_count": 0, "organization": {}, "repo_homepage": "http://pytablereader.rtfd.io/", "stargazers_count": 25, "topics": ["csv", "excel", "google-sheets", "html", "json", "ltsv", "markdown", "mediawiki", "pandas", "pandas-dataframe", "python-library", "reader", "sqlite", "table", "tsv"], "participation": [0, 0, 9, 24, 0, 9, 31, 7, 0, 0, 0, 20, 3, 4, 26, 9, 14, 6, 10, 0, 0, 0, 0, 0, 0, 4, 0, 0, 4, 0, 2, 15, 14, 0, 0, 0, 0, 0, 0, 0, 0, 0, 0, 0, 0, 0, 0, 0, 0, 0, 0, 0], "commits_last_year": 211, "latest_tag": "v0.16.0", "branches_count": 1, "pulls_count": 0, "subscribers_count": 3, "license": {"key": "mit", "name": "MIT License", "spdx_id": "MIT", "url": "https://api.github.com/licenses/mit"}, "contributors_count": 2, "tags_count": 55, "open_issues": {"labels": [], "data": []}}
