{
    "id": "thombashi/tcconfig",
    "fetched_at": "2019-02-28T15:17:30",
    "data_version": 2,
    "result": "success",
    "avatar_url": "https://avatars0.githubusercontent.com/u/15517661?v=4",
    "card_type": "Repository",
    "created_at": "2016-01-17T16:24:09",
    "description": "A tc command wrapper. Make it easy to set up traffic control of network bandwidth/latency/packet-loss/packet-corruption/etc. to a network-interface/Docker-container(veth).",
    "emojis": {},
    "html_url": "https://github.com/thombashi/tcconfig",
    "name": "tcconfig",
    "updated_at": "2019-02-26T13:28:23",
    "forks_count": 35,
    "has_issues": true,
    "has_wiki": false,
    "language": "Python",
    "languages": {
        "labels": [
            "Python",
            "Shell",
            "Makefile"
        ],
        "data": [
            283558,
            2341,
            908
        ]
    },
    "languages_count": 3,
    "owner_name": "Tsuyoshi Hombashi",
    "owner_html_url": "https://github.com/thombashi",
    "open_issues_count": 5,
    "organization": {},
    "repo_homepage": "https://tcconfig.rtfd.io/",
    "stargazers_count": 335,
    "topics": [
        "cli-app",
        "docker",
        "linux",
        "network",
        "tc",
        "traffic-shaping",
        "wrapper"
    ],
    "participation": [
        0,
        0,
        0,
        0,
        0,
        45,
        0,
        7,
        5,
        54,
        0,
        1,
        6,
        0,
        0,
        0,
        0,
        7,
        0,
        35,
        4,
        8,
        9,
        1,
        10,
        0,
        0,
        13,
        0,
        4,
        5,
        0,
        48,
        0,
        0,
        0,
        0,
        0,
        0,
        0,
        0,
        0,
        8,
        11,
        7,
        8,
        13,
        0,
        17,
        23,
        0,
        9
    ],
    "commits_last_year": 358,
    "latest_tag": "v0.21.9",
    "branches_count": 1,
    "pulls_count": 0,
    "subscribers_count": 15,
    "license": {
        "key": "mit",
        "name": "MIT License",
        "spdx_id": "MIT",
        "url": "https://api.github.com/licenses/mit",
        "node_id": "MDc6TGljZW5zZTEz"
    },
    "contributors_count": 7,
    "tags_count": 65,
    "open_issues": {
        "labels": [
            "not set",
            "bug",
            "enhancement"
        ],
        "data": [
            3,
            1,
            1
        ]
    }
}
