{"has_wiki": false, "forks_count": 9035, "updated_at": "2017-03-21T14:29:42", "owner_html_url": "https://github.com/daneden", "id": "daneden/animate.css", "license": {"spdx_id": "MIT", "url": "https://api.github.com/licenses/mit", "featured": true, "name": "MIT License", "key": "mit"}, "tags_count": 22, "languages": {"labels": ["CSS", "JavaScript"], "data": [23005, 2509]}, "data_version": 1, "pulls_count": 24, "latest_tag": "v3.1.0", "stargazers_count": 40191, "emojis": {}, "participation": [1, 0, 0, 1, 0, 4, 0, 0, 0, 0, 0, 6, 0, 0, 0, 2, 0, 0, 0, 0, 0, 0, 1, 9, 0, 0, 8, 5, 0, 0, 0, 0, 0, 0, 0, 0, 0, 0, 0, 0, 0, 0, 0, 0, 0, 0, 0, 0, 0, 0, 0, 0], "owner_name": "Daniel Eden", "repo_homepage": "daneden.github.io/animate.css", "subscribers_count": 2073, "html_url": "https://github.com/daneden/animate.css", "languages_count": 2, "language": "CSS", "commits_last_year": 37, "contributors_count": 69, "fetched_at": "2017-03-21T23:51:16", "has_issues": true, "repo_description": "A cross-browser library of CSS animations. As easy to use as an easy thing.", "open_issues_count": 41, "name": "animate.css", "branches_count": 4, "created_at": "2011-10-12T10:07:38", "card_type": "repository", "avatar_url": "https://avatars0.githubusercontent.com/u/439365?v=3", "open_issues": {"labels": ["not set", "improvement", "documentation", "feature request", "demo site", "bug fix", "new animation"], "data": [31, 5, 3, 3, 1, 1, 1]}, "organization": {}}
